phylum_ci/__init__.py
phylum_ci/cli.py
phylum_ci-0.0.1.dist-info/entry_points.txt
phylum_ci-0.0.1.dist-info/LICENSE
phylum_ci-0.0.1.dist-info/WHEEL
phylum_ci-0.0.1.dist-info/METADATA
phylum_ci-0.0.1.dist-info/RECORD
