Metadata-Version: 2.1
Name: phylum-ci
Version: 0.0.1
Summary: Utilities for Phylum integrations
Home-page: https://phylum.io/
License: MIT
Keywords: dependency,security,CI,integration
Author: Phylum, Inc.
Author-email: engineering@phylum.io
Requires-Python: >=3.7,<4.0
Classifier: Development Status :: 2 - Pre-Alpha
Classifier: Environment :: Console
Classifier: Intended Audience :: Developers
Classifier: License :: OSI Approved :: MIT License
Classifier: Natural Language :: English
Classifier: Programming Language :: Python :: 3
Classifier: Programming Language :: Python :: 3.10
Classifier: Programming Language :: Python :: 3.7
Classifier: Programming Language :: Python :: 3.8
Classifier: Programming Language :: Python :: 3.9
Classifier: Topic :: Security
Classifier: Topic :: Software Development
Classifier: Topic :: Software Development :: Quality Assurance
Project-URL: Documentation, https://docs.phylum.io/
Project-URL: Issue Tracker, https://github.com/phylum-dev/phylum-ci/issues
Project-URL: Repository, https://github.com/phylum-dev/phylum-ci
